akin/__init__.py
akin/_data_structures.py
akin/lsh.py
akin/minhash.py
akin-1.0.1.dist-info/LICENSE
akin-1.0.1.dist-info/METADATA
akin-1.0.1.dist-info/WHEEL
akin-1.0.1.dist-info/top_level.txt
akin-1.0.1.dist-info/RECORD
