Metadata-Version: 2.2
Name: akin
Version: 1.0.1
Summary: Akin is a Python library for detecting near-duplicate texts using min-hashing and locality sensitive hashing.
Project-URL: Homepage, https://github.com/justinbt1/Akin
License-File: LICENSE
Requires-Dist: numpy
Requires-Dist: cython
Requires-Dist: mmh3
Requires-Dist: tqdm
Dynamic: description
Dynamic: description-content-type
Dynamic: project-url
Dynamic: requires-dist
Dynamic: summary
